{
	"pages": [
		// {
		// 	"path": "pages/dengru/dengru",
		// 	"style": {
		// 		"navigationBarTitleText": "快帮网"
		// 	}
		// },
		// {
		// 	"path": "pages/shouye/shouye",
		// 	"style": {
		// 		"navigationBarTitleText": "快帮网"
		// 	}
		// },
		
		// {
		// 	"path": "pages/fabu/fabu",
		// 	"style": {
		// 		"navigationBarTitleText": "发布"
		// 	}
		// },
		// {
		// 	"path": "pages/chazhao/chazhao",
		// 	"style": {
		// 		"navigationBarTitleText": "房产"
		// 	}
		// },
		{
			"path": "pages/xiangqing/xiangqing",
			"style": {
				"navigationBarTitleText": "商铺详情"
			}
		},
		{
			"path": "pages/geren/yidengru-1",
			"style": {
				"navigationBarTitleText": "个人中心"
			}
		}
	],
	"globalStyle": {
		"navigationBarTextStyle": "black",
		"navigationBarTitleText": "uni-app",
		"navigationBarBackgroundColor": "#F8F8F8",
		"backgroundColor": "#F8F8F8"
	}
}
